sit_rezervo/__init__.py
sit_rezervo/api.py
sit_rezervo/auth.py
sit_rezervo/booking.py
sit_rezervo/cli.py
sit_rezervo/config.py
sit_rezervo/consts.py
sit_rezervo/cron_generator.py
sit_rezervo/errors.py
sit_rezervo/main.py
sit_rezervo/notify/__init__.py
sit_rezervo/notify/notify.py
sit_rezervo/notify/slack.py
sit_rezervo/notify/utils.py
sit_rezervo/utils/__init__.py
sit_rezervo/utils/time_utils.py
sit_rezervo-0.1.0.dist-info/entry_points.txt
sit_rezervo-0.1.0.dist-info/METADATA
sit_rezervo-0.1.0.dist-info/WHEEL
sit_rezervo-0.1.0.dist-info/RECORD
