Metadata-Version: 2.1
Name: sit-rezervo
Version: 0.1.0
Summary: Automatic booking of Sit Trening group classes
Home-page: https://github.com/mathiazom/sit-rezervo
Author: Mathias Oterhals Myklebust
Author-email: mathias@oterbust.no
Requires-Python: >=3.10,<4.0
Classifier: Development Status :: 4 - Beta
Classifier: Intended Audience :: Developers
Classifier: License :: OSI Approved :: MIT License
Classifier: Operating System :: OS Independent
Classifier: Programming Language :: Python :: 3
Classifier: Programming Language :: Python :: 3.10
Classifier: Programming Language :: Python :: 3.11
Classifier: Programming Language :: Python :: 3.10
Requires-Dist: dataclass-wizard[yaml] (>=0.22.2,<0.23.0)
Requires-Dist: fastapi (>=0.88.0,<0.89.0)
Requires-Dist: pydantic (>=1.10.2,<2.0.0)
Requires-Dist: python-multipart (>=0.0.5,<0.0.6)
Requires-Dist: pytz (>=2022.7,<2023.0)
Requires-Dist: requests (>=2.28.1,<3.0.0)
Requires-Dist: slack-sdk (>=3.19.5,<4.0.0)
Requires-Dist: typer (>=0.7.0,<0.8.0)
Requires-Dist: uvicorn (>=0.20.0,<0.21.0)
Project-URL: Bug Tracker, https://github.com/mathiazom/sit-rezervo/issues
Project-URL: Repository, https://github.com/mathiazom/sit-rezervo
